dllaby/__init__.py
dllaby/hari.py
dllaby-0.0.3.dist-info/METADATA
dllaby-0.0.3.dist-info/WHEEL
dllaby-0.0.3.dist-info/top_level.txt
dllaby-0.0.3.dist-info/RECORD
