Metadata-Version: 2.4
Name: dllaby
Version: 0.0.3
Summary: DL lab
Author: Hari
Author-email: <hari.velusmy@gmail.com>
Keywords: python
Classifier: Development Status :: 1 - Planning
Classifier: Intended Audience :: Developers
Classifier: Programming Language :: Python :: 3
Classifier: Operating System :: Unix
Classifier: Operating System :: MacOS :: MacOS X
Classifier: Operating System :: Microsoft :: Windows
Dynamic: author
Dynamic: author-email
Dynamic: classifier
Dynamic: description-content-type
Dynamic: keywords
Dynamic: summary
